neural_network/__init__.py
neural_network/activation.py
neural_network/loss.py
neural_network/neural_network.py
neural_network/utility.py
neural_network-0.1.1.dist-info/LICENSE
neural_network-0.1.1.dist-info/METADATA
neural_network-0.1.1.dist-info/WHEEL
neural_network-0.1.1.dist-info/top_level.txt
neural_network-0.1.1.dist-info/RECORD
