Metadata-Version: 2.1
Name: neural-network
Version: 0.1.1
Summary: A Neural Network framework for building Multi-layer Perceptron model.
Home-page: https://github.com/AnhQuoc533/neural-network
Author: Anh Quoc
Author-email: lhoanganhquoc@gmail.com
License: MIT
Project-URL: Bug Reports, https://github.com/AnhQuoc533/neural-network/issues
Project-URL: Funding, https://donate.pypi.org
Project-URL: Source, https://github.com/AnhQuoc533/neural-network
Keywords: neural-network,deep-learning,machine-learning,neural-networks,machine-learning-algorithms
Classifier: Development Status :: 3 - Alpha
Classifier: License :: OSI Approved :: MIT License
Classifier: Programming Language :: Python :: 3
Classifier: Programming Language :: Python :: 3.8
Classifier: Programming Language :: Python :: 3.9
Classifier: Programming Language :: Python :: 3.10
Requires-Python: >=3.8
License-File: LICENSE
Requires-Dist: numpy (>=1.22.1)
Requires-Dist: matplotlib (>=3.5.1)
